rgcosm/__init__.py
rgcosm/__main__.py
rgcosm/convert.py
rgcosm/geocoder.py
rgcosm-0.1.2.dist-info/LICENSE
rgcosm-0.1.2.dist-info/METADATA
rgcosm-0.1.2.dist-info/WHEEL
rgcosm-0.1.2.dist-info/entry_points.txt
rgcosm-0.1.2.dist-info/top_level.txt
rgcosm-0.1.2.dist-info/RECORD
