Metadata-Version: 2.1
Name: rgcosm
Version: 0.1.2
Summary: rgcosm simple reverse geocoding library from converted osm(.pbf) GIS data by converter in this lib
Home-page: https://github.com/BlackCatDevel0per/rgcosm
Author: bcdev
Author-email: bcdev@mail.ru
Project-URL: Bug Tracker, https://github.com/BlackCatDevel0per/rgcosm/issues
Classifier: Environment :: Console
Classifier: Programming Language :: Python :: 3
Classifier: License :: OSI Approved :: Apache Software License
Classifier: Operating System :: OS Independent
Classifier: Topic :: Utilities
Classifier: Typing :: Typed
Classifier: Topic :: Text Processing :: Filters
Classifier: Topic :: Software Development :: Libraries :: Python Modules
Requires-Python: >=3.7
License-File: LICENSE
Requires-Dist: osmium (>=3.6.0)
